{
  "users": [
    {
      "id": "1",
      "name": {
        "first": "Alyson",
        "last": "Cervantes"
      },
      "username": "user1",
      "email": "alyson.cervantes@undefined.com",
      "location": "Deltaville, California",
      "password": "password",
      "image": "http://via.placeholder.com/350x150"
    },
    {
      "id": "2",
      "name": {
        "first": "Page",
        "last": "Mclean"
      },
      "username": "user2",
      "email": "page.mclean@undefined.ca",
      "location": "Lumberton, Virginia",
      "password": "password",
      "image": "http://via.placeholder.com/350x150"
    },
    {
      "id": "3",
      "name": {
        "first": "Inez",
        "last": "Randall"
      },
      "username": "user3",
      "email": "inez.randall@undefined.net",
      "location": "Norris, American Samoa",
      "password": "password",
      "image": "https://scontent-ort2-2.xx.fbcdn.net/v/t31.0-8/19787380_10213890411117908_3086033669035682291_o.jpg?_nc_cat=0&oh=5953b46e032171c009250347cb4134ad&oe=5BBE48DA"
    },
    {
      "id": "4",
      "name": {
        "first": "Erika",
        "last": "Chambers"
      },
      "username": "user4",
      "email": "erika.chambers@undefined.org",
      "location": "Saddlebrooke, Missouri",
      "password": "password",
      "image": "http://via.placeholder.com/350x150"
    },
    {
      "id": "5",
      "name": {
        "first": "Ramona",
        "last": "Carter"
      },
      "username": "user5",
      "email": "ramona.carter@undefined.us",
      "location": "Hobucken, Maryland",
      "password": "password",
      "image": "http://via.placeholder.com/350x150"
    },
    {
      "id": "6",
      "name": {
        "first": "Holmes",
        "last": "Lindsay"
      },
      "username": "user6",
      "email": "holmes.lindsay@undefined.biz",
      "location": "Longbranch, Massachusetts",
      "password": "password",
      "image": "http://via.placeholder.com/350x150"
    },
    {
      "id": "7",
      "name": {
        "first": "Murphy",
        "last": "Lynn"
      },
      "username": "user7",
      "email": "murphy.lynn@undefined.name",
      "location": "Movico, Rhode Island",
      "password": "password",
      "image": "http://via.placeholder.com/350x150"
    },
    {
      "id": "8",
      "name": {
        "first": "Bonner",
        "last": "George"
      },
      "username": "user8",
      "email": "bonner.george@undefined.biz",
      "location": "Sehili, Oregon",
      "password": "password",
      "image": "http://via.placeholder.com/350x150"
    },
    {
      "id": "9",
      "name": {
        "first": "Kent",
        "last": "Branch"
      },
      "username": "user9",
      "email": "kent.branch@undefined.co.uk",
      "location": "Blodgett, New York",
      "password": "password",
      "image": "http://via.placeholder.com/350x150"
    },
    {
      "id": "10",
      "name": {
        "first": "Cotton",
        "last": "Watts"
      },
      "username": "user10",
      "email": "cotton.watts@undefined.info",
      "location": "Hollymead, Colorado",
      "password": "password",
      "image": "http://via.placeholder.com/350x150"
    }
  ],
  "friendships": [
    {
      "id": "1",
      "user1Id": "1",
      "user2Id": "2"
    },
    {
      "id": "2",
      "user1Id": "1",
      "user2Id": "3"
    },
    {
      "id": "3",
      "user1Id": "2",
      "user2Id": "4"
    },
    {
      "id": "4",
      "user1Id": "4",
      "user2Id": "7"
    },
    {
      "id": "5",
      "user1Id": "10",
      "user2Id": "8"
    },
    {
      "id": "6",
      "user1Id": "6",
      "user2Id": "5"
    },
    {
      "id": "7",
      "user1Id": "9",
      "user2Id": "10"
    }
  ],
  "friendRequests": [
    {
      "id": "1",
      "userId": "1",
      "receiverId": "2"
    }
  ],
  "posts": [
    {
      "id": "1",
      "userId": "1",
      "timeStamp": "",
      "content": "Qui laboris cillum non ut incididunt id esse. Ut officia velit aliqua ullamco cupidatat deserunt consectetur ipsum officia.",
      "image": "http://via.placeholder.com/350x150",
      "receiverId": "null",
      "private": "false"
    },
    {
      "id": "2",
      "userId": "2",
      "timeStamp": "",
      "content": "Et elit nostrud dolor commodo nulla. Duis magna elit eiusmod cupidatat culpa nisi commodo.",
      "image": "http://via.placeholder.com/350x150",
      "receiverId": "3",
      "private": "true"
    },
    {
      "id": "3",
      "userId": "3",
      "timeStamp": "",
      "content": "Irure laboris duis sint pariatur. Voluptate mollit tempor aliqua amet exercitation ullamco excepteur.",
      "image": "http://via.placeholder.com/350x150",
      "receiverId": "null",
      "private": "false"
    },
    {
      "id": "4",
      "userId": "4",
      "timeStamp": "",
      "content": "Exercitation eu ipsum aute laborum aliqua aliqua. Anim reprehenderit cillum ex id voluptate irure consectetur est.",
      "image": "http://via.placeholder.com/350x150",
      "receiverId": "5",
      "private": "true"
    },
    {
      "id": "5",
      "userId": "5",
      "timeStamp": "",
      "content": "Minim esse minim qui enim fugiat nostrud elit magna laboris enim do cupidatat. Duis minim sit ipsum deserunt consectetur eu tempor consectetur in exercitation pariatur.",
      "image": "http://via.placeholder.com/350x150",
      "receiverId": "null",
      "private": "false"
    },
    {
      "id": "6",
      "userId": "6",
      "timeStamp": "",
      "content": "Minim amet nostrud et sit. Officia eiusmod eiusmod reprehenderit occaecat occaecat deserunt.",
      "image": "http://via.placeholder.com/350x150",
      "receiverId": "null",
      "private": "false"
    },
    {
      "id": "7",
      "userId": "7",
      "timeStamp": "",
      "content": "Voluptate fugiat pariatur ipsum duis esse nostrud adipisicing aute et culpa excepteur laborum. Cupidatat quis proident cillum in veniam esse tempor est velit qui excepteur aliqua laborum sint.",
      "image": "http://via.placeholder.com/350x150",
      "receiverId": "4",
      "private": "true"
    },
    {
      "id": "8",
      "userId": "8",
      "timeStamp": "",
      "content": "Fugiat id occaecat id ut cillum. Duis in deserunt sit culpa duis est aute aliquip ea.",
      "image": "http://via.placeholder.com/350x150",
      "receiverId": "8",
      "private": "true"
    },
    {
      "id": "9",
      "userId": "9",
      "timeStamp": "",
      "content": "Et amet enim est irure qui. Dolor ullamco sint ut sint sint laboris sit occaecat non ea dolore nulla et.",
      "image": "http://via.placeholder.com/350x150",
      "receiverId": "null",
      "private": "false"
    },
    {
      "id": "10",
      "userId": "10",
      "timeStamp": "",
      "content": "Nostrud enim est eiusmod quis. Dolore aliqua sunt ullamco aute eiusmod dolore enim exercitation occaecat proident.",
      "image": "http://via.placeholder.com/350x150",
      "receiverId": "null",
      "private": "false"
    },
    {
      "userId": "1",
      "timeStamp": "2018-06-01T18:44:15.294Z",
      "image": "",
      "receiverId": "null",
      "private": "true",
      "id": "u9UIX5o"
    },
    {
      "userId": "1",
      "timeStamp": "2018-06-01T18:44:16.116Z",
      "image": "",
      "receiverId": "null",
      "private": "true",
      "id": "xK1pYci"
    },
    {
      "userId": "1",
      "timeStamp": "2018-06-01T18:44:16.829Z",
      "image": "",
      "receiverId": "null",
      "private": "false",
      "id": "V2xQwrp"
    }
  ],
  "followships": [
    {
      "id": "1",
      "userId": "4",
      "followedId": "6"
    },
    {
      "id": "2",
      "userId": "1",
      "followedId": "10"
    },
    {
      "id": "3",
      "userId": "2",
      "followedId": "9"
    },
    {
      "id": "4",
      "userId": "8",
      "followedId": "1"
    }
  ],
  "events": [
    {
      "id": "1",
      "userId": "3",
      "name": "Party",
      "date": "June 15",
      "startTime": "6:00",
      "endTime": "9:00"
    },
    {
      "id": "2",
      "userId": "4",
      "name": "Party",
      "date": "June 12",
      "startTime": "6:00",
      "endTime": "9:00"
    },
    {
      "id": "3",
      "userId": "5",
      "name": "Party",
      "date": "May 30",
      "startTime": "6:00",
      "endTime": "9:00"
    },
    {
      "id": "4",
      "userId": "6",
      "name": "Party",
      "date": "June 18",
      "startTime": "6:00",
      "endTime": "9:00"
    },
    {
      "id": "5",
      "userId": "7",
      "name": "Party",
      "date": "June 22",
      "startTime": "6:00",
      "endTime": "9:00"
    }
  ],
  "likes": [
    {
      "id": "1",
      "userId": "1",
      "publicPostId": "3"
    },
    {
      "id": "2",
      "userId": "2",
      "publicPostId": "10"
    },
    {
      "id": "3",
      "userId": "2",
      "publicPostId": "4"
    },
    {
      "id": "4",
      "userId": "6",
      "publicPostId": "1"
    },
    {
      "id": "5",
      "userId": "8",
      "publicPostId": "7"
    }
  ],
  "ads": [
    {
      "id": 1,
      "company": "Euron",
      "content": "Incididunt sunt in officia dolor quis irure aliquip laboris cupidatat aute in ad eiusmod. Consectetur nisi et ea non consequat aliquip eiusmod adipisicing dolor tempor. Cupidatat officia consectetur reprehenderit consequat aliqua fugiat magna. Voluptate occaecat ipsum culpa irure voluptate aliqua ipsum in Lorem officia enim qui nostrud. Pariatur ea aliqua dolore duis cillum exercitation laboris et fugiat enim reprehenderit id cupidatat exercitation. Nulla velit reprehenderit ad consequat sit nulla do adipisicing veniam. Anim elit dolor minim ipsum qui qui id.",
      "title": "dolor velit"
    },
    {
      "id": 2,
      "company": "Webiotic",
      "content": "Laborum aliquip reprehenderit enim ex duis voluptate ad. Deserunt mollit ad Lorem ullamco elit voluptate enim ex sit. Tempor labore et consequat sit pariatur qui reprehenderit non. Laboris dolor duis dolor ullamco laboris quis cillum dolor est eu. Duis anim labore occaecat nostrud sunt quis duis quis nulla proident.",
      "title": "nulla eiusmod"
    },
    {
      "id": 3,
      "company": "Ersum",
      "content": "Eu excepteur ut elit minim est amet esse occaecat nisi amet irure. Velit sunt ipsum do esse nulla qui ipsum sunt laboris pariatur quis laborum ut. Lorem id nisi irure ullamco cillum laboris laborum tempor amet eu mollit deserunt anim enim. Magna non occaecat ea incididunt sunt aliquip elit reprehenderit et. In aute sint reprehenderit eiusmod eu qui nulla id culpa commodo consequat. Magna aliquip consequat reprehenderit quis magna fugiat minim Lorem incididunt reprehenderit laboris tempor fugiat. Velit magna occaecat eiusmod sint in.",
      "title": "Lorem culpa"
    },
    {
      "id": 4,
      "company": "Pharmex",
      "content": "Exercitation esse non dolor ut esse anim exercitation aliquip incididunt sit laborum culpa labore eiusmod. Deserunt consectetur do ex aliquip ea commodo ex labore duis duis consequat irure. Consequat nulla tempor dolor aliqua officia magna.",
      "title": "reprehenderit qui"
    },
    {
      "id": 5,
      "company": "Emergent",
      "content": "Ut eiusmod ut tempor nulla ex. Esse aute ea pariatur magna qui in. Excepteur pariatur reprehenderit culpa magna irure.",
      "title": "id exercitation"
    }
  ]
}